{
  "这是什么": "这是一份单卷运行记录，用来说明本卷拉题、质检、修复和输出文件的情况。",
  "试卷信息": {
    "卷号": "第2卷",
    "卷型": "考点训练卷",
    "课程": "电工技术基础与技能",
    "专题": "电路基本概念与定律",
    "考点": "电流、电压与电位",
    "地区": "重庆市",
    "考类": "电子信息类",
    "规划表": "C:\\Users\\zxxk\\Desktop\\考纲百套卷\\04_生成输出\\生产规划\\重庆市 电子信息类\\重庆市_电子信息类_考点规划总表.xlsx"
  },
  "输入材料记录": {
    "一句话说明": "已在组卷待质检目录找到这卷的材料，直接进入拆题和质检。",
    "查找目录": "C:\\Users\\zxxk\\Desktop\\考纲百套卷\\04_生成输出\\组卷待质检\\重庆市 电子信息类",
    "找到待质检文件": true,
    "文件路径": "C:\\Users\\zxxk\\Desktop\\考纲百套卷\\04_生成输出\\组卷待质检\\重庆市 电子信息类\\第2卷_repaired.docx"
  },
  "最后更新时间": "2026-06-29 11:50:46",
  "API拉题记录": {
    "一句话说明": "映射表里没有本卷可用的知识点 ID，所以没有调用题库 API。",
    "是否调用API": false,
    "跳过原因": "映射表没有知识点 ID",
    "映射表路径": "C:\\Users\\dell\\Desktop\\考纲百套卷生成工具包\\考纲百套卷\\04_生成输出\\生产规划\\重庆市 电子信息类\\重庆市_电子信息类_映射表.xlsx"
  },
  "拆题和初检记录": {
    "一句话说明": "【修复前】第1轮质检完成：拆出 42 题，通过 42 题，失败 0 题，警告 0 题，全卷问题 0 个",
    "拆出题数": 42,
    "拆题结果文件": "C:\\Users\\zxxk\\Desktop\\考纲百套卷\\04_生成输出\\清洗结果\\重庆市 电子信息类\\组卷拆题\\第2卷_考点训练卷_questions.json",
    "修复前质检报告": "C:\\Users\\zxxk\\Desktop\\考纲百套卷\\04_生成输出\\质检报告\\重庆市 电子信息类\\电工技术基础与技能\\修复前\\第2卷_质检报告.md",
    "初检通过题数": 42,
    "初检失败题数": 0,
    "初检警告题数": 0,
    "初检全卷问题数": 0
  },
  "修复记录": {
    "一句话说明": "质检后没有发现需要 AI 修复的题目。",
    "修复前": {
      "失败题数": 0,
      "警告题数": 0,
      "全卷问题数": 0
    },
    "实际修复轮数": 0,
    "修复成功题数": 0,
    "修复后": {
      "失败题数": 0,
      "警告题数": 0,
      "全卷问题数": 0
    }
  },
  "质检修复后的结果": {
    "一句话说明": "【修复前】质检完成：逐题通过 42 题，失败 0 题，警告 0 题，全卷问题 0 个，通过质检",
    "最终质检报告": "C:\\Users\\zxxk\\Desktop\\考纲百套卷\\04_生成输出\\质检报告\\重庆市 电子信息类\\电工技术基础与技能\\修复前\\第2卷_质检报告.md",
    "最终题目文件": "C:\\Users\\zxxk\\Desktop\\考纲百套卷\\04_生成输出\\清洗结果\\重庆市 电子信息类\\组卷拆题\\第2卷_考点训练卷_questions.json",
    "修复后仍有问题数": 0,
    "需要人工复核题数": 0,
    "当前状态": "质检已通过，等待生成最终文件"
  }
}